dsp/__init__.py
dsp/cone_transforms.py
dsp/cvxpy_integration.py
dsp/local.py
dsp/parser.py
dsp/problem.py
dsp/saddle_atoms.py
dsp/saddle_extremum.py
dsp/semi_infinite_canon.py
dsp/utils.py
tests/__init__.py
tests/test_cone_transforms.py
tests/test_cvxpy_integration.py
tests/test_dsp.py
tests/test_examples.py
tests/test_is_dsp.py
tests/test_minimizemaximize.py
tests/test_parser.py
tests/test_pathology.py
tests/test_quasidef_quad_form.py
tests/test_saddle_quad_form.py
tests/test_snippets.py
tests/test_weighted_log_sum_exp.py
tests/test_weighted_norm2.py
dsp_cvxpy-0.3.0.dist-info/LICENSE
dsp_cvxpy-0.3.0.dist-info/METADATA
dsp_cvxpy-0.3.0.dist-info/WHEEL
dsp_cvxpy-0.3.0.dist-info/top_level.txt
dsp_cvxpy-0.3.0.dist-info/zip-safe
dsp_cvxpy-0.3.0.dist-info/RECORD
