Metadata-Version: 2.1
Name: dsp-cvxpy
Version: 0.3.0
Summary: Disciplined Saddle Programming
Home-page: https://github.com/cvxgrp/dsp
Author: Philipp Schiele, Eric Luxenberg, Stephen Boyd
Author-email: philipp.schiele@stat.uni-muenchen.de, ericlux@stanford.edu, boyd@stanford.edu
License: Apache License, Version 2.0
License-File: LICENSE
Requires-Dist: cvxpy >=1.3
Requires-Dist: numpy
Requires-Dist: scipy
Provides-Extra: dev
Requires-Dist: tox ; extra == 'dev'
